upyls/__init__.py
upyls/limited_list.py
upyls/multi_ini_parser.py
upyls/unit_of_work.py
upyls-0.1.0.dist-info/LICENSE
upyls-0.1.0.dist-info/METADATA
upyls-0.1.0.dist-info/WHEEL
upyls-0.1.0.dist-info/top_level.txt
upyls-0.1.0.dist-info/RECORD
