Metadata-Version: 2.1
Name: upyls
Version: 0.1.0
Summary: A collection of python utilities
Home-page: https://github.com/Corvan/upyls
Author: Lars Liedtke
Author-email: LarsLiedtke@gmx.de
License: LGPL v. 2.1
Platform: UNKNOWN
Classifier: Programming Language :: Python :: 3.7
Classifier: License :: OSI Approved :: GNU Lesser General Public License v2 (LGPLv2)
Classifier: Operating System :: OS Independent
Classifier: Topic :: Software Development :: Libraries :: Python Modules
Classifier: Topic :: Utilities
